transhette
