Metadata-Version: 1.0
Name: transhette
Version: 0.5.8
Summary: django-rosetta fork for translating Django .po catalogs, with a lot of improvements compared with rosetta
Home-page: https://tracpub.yaco.es/djangoapps/wiki/Transhette
Author: Yaco Sistemas S.L.
Author-email: esanchez@yaco.es
License: LGPL 3
Keywords: django translation i18n rosetta
Platform: UNKNOWN
Classifier: Development Status :: 4 - Beta
Classifier: Framework :: Django
Classifier: License :: OSI Approved :: GNU Library or Lesser General Public License (LGPL)
